LiveChessCloud/__init__.py
LiveChessCloud/download.py
LiveChessCloud/export.py
LiveChessCloud/help.py
LiveChessCloud-0.1.0.dist-info/LICENSE
LiveChessCloud-0.1.0.dist-info/METADATA
LiveChessCloud-0.1.0.dist-info/WHEEL
LiveChessCloud-0.1.0.dist-info/entry_points.txt
LiveChessCloud-0.1.0.dist-info/top_level.txt
LiveChessCloud-0.1.0.dist-info/RECORD
